aiologging/__init__.py
aiologging-1.0.1.dist-info/METADATA
aiologging-1.0.1.dist-info/WHEEL
aiologging-1.0.1.dist-info/top_level.txt
aiologging-1.0.1.dist-info/RECORD
