Metadata-Version: 2.2
Name: aiologging
Version: 1.0.1
Summary: Asynchronous module for logging in python.
Home-page: https://github.com/users/zvenios/projects/2
Author: zvenios
Author-email: kont.05.vladdd@gmail.com
Project-URL: GitGub, https://github.com/zvenios
Keywords: aio log logger logging aiolog aiologger aiologging
Requires-Python: >=3.11
Dynamic: author
Dynamic: author-email
Dynamic: description
Dynamic: description-content-type
Dynamic: home-page
Dynamic: keywords
Dynamic: project-url
Dynamic: requires-python
Dynamic: summary
